sentinelhub/.utmzones.geojson
sentinelhub/__init__.py
sentinelhub/_version.py
sentinelhub/areas.py
sentinelhub/base.py
sentinelhub/commands.py
sentinelhub/config.py
sentinelhub/constants.py
sentinelhub/data_collections.py
sentinelhub/data_collections_bands.py
sentinelhub/data_utils.py
sentinelhub/decoding.py
sentinelhub/evalscript.py
sentinelhub/exceptions.py
sentinelhub/geo_utils.py
sentinelhub/geometry.py
sentinelhub/io_utils.py
sentinelhub/py.typed
sentinelhub/testing_utils.py
sentinelhub/time_utils.py
sentinelhub/types.py
sentinelhub/api/__init__.py
sentinelhub/api/base.py
sentinelhub/api/base_request.py
sentinelhub/api/byoc.py
sentinelhub/api/catalog.py
sentinelhub/api/fis.py
sentinelhub/api/ogc.py
sentinelhub/api/opensearch.py
sentinelhub/api/process.py
sentinelhub/api/statistical.py
sentinelhub/api/utils.py
sentinelhub/api/wfs.py
sentinelhub/api/batch/__init__.py
sentinelhub/api/batch/base.py
sentinelhub/api/batch/process.py
sentinelhub/api/batch/process_v2.py
sentinelhub/api/batch/statistical.py
sentinelhub/api/batch/utils.py
sentinelhub/aws/__init__.py
sentinelhub/aws/batch.py
sentinelhub/aws/client.py
sentinelhub/aws/commands.py
sentinelhub/aws/constants.py
sentinelhub/aws/data.py
sentinelhub/aws/data_safe.py
sentinelhub/aws/request.py
sentinelhub/download/__init__.py
sentinelhub/download/client.py
sentinelhub/download/handlers.py
sentinelhub/download/models.py
sentinelhub/download/rate_limit.py
sentinelhub/download/sentinelhub_client.py
sentinelhub/download/sentinelhub_statistical_client.py
sentinelhub/download/session.py
sentinelhub/geopedia/__init__.py
sentinelhub/geopedia/core.py
sentinelhub/geopedia/request.py
sentinelhub-3.11.0.dist-info/METADATA
sentinelhub-3.11.0.dist-info/WHEEL
sentinelhub-3.11.0.dist-info/entry_points.txt
sentinelhub-3.11.0.dist-info/licenses/LICENSE.md
sentinelhub-3.11.0.dist-info/RECORD
