Metadata-Version: 2.3
Name: sentinelhub
Version: 3.11.0
Summary: Python API for Sentinel Hub
Project-URL: Homepage, https://github.com/sentinel-hub/sentinelhub-py
Project-URL: Documentation, https://sentinelhub-py.readthedocs.io
Project-URL: Issues, https://github.com/sentinel-hub/sentinelhub-py/issues
Project-URL: Source, https://github.com/sentinel-hub/sentinelhub-py
Project-URL: Forum, https://forum.sentinel-hub.com
Author-email: Sinergise EO research team <eoresearch@sinergise.com>
License: MIT License
License-File: LICENSE.md
Classifier: Development Status :: 5 - Production/Stable
Classifier: Intended Audience :: Developers
Classifier: Intended Audience :: Education
Classifier: Intended Audience :: Science/Research
Classifier: License :: OSI Approved :: MIT License
Classifier: Operating System :: MacOS
Classifier: Operating System :: Microsoft :: Windows
Classifier: Operating System :: Unix
Classifier: Programming Language :: Python
Classifier: Programming Language :: Python :: 3
Classifier: Programming Language :: Python :: 3.8
Classifier: Programming Language :: Python :: 3.9
Classifier: Programming Language :: Python :: 3.10
Classifier: Programming Language :: Python :: 3.11
Classifier: Topic :: Scientific/Engineering
Classifier: Topic :: Software Development
Requires-Python: >=3.8
Requires-Dist: aenum>=2.1.4
Requires-Dist: click
Requires-Dist: dataclasses-json
Requires-Dist: numpy<2
Requires-Dist: oauthlib
Requires-Dist: pillow>=9.2.0
Requires-Dist: pyproj>=2.2.0
Requires-Dist: python-dateutil
Requires-Dist: requests-oauthlib>=1.0.0
Requires-Dist: requests>=2.27.0
Requires-Dist: shapely
Requires-Dist: tifffile>=2020.9.30
Requires-Dist: tomli
Requires-Dist: tomli-w
Requires-Dist: tqdm
Requires-Dist: typing-extensions>=4.5.0
Requires-Dist: utm
Provides-Extra: aws
Requires-Dist: boto3; extra == 'aws'
Requires-Dist: botocore; extra == 'aws'
Provides-Extra: dev
Requires-Dist: basemap; extra == 'dev'
Requires-Dist: boto3-stubs>=1.20.0; extra == 'dev'
Requires-Dist: build; extra == 'dev'
Requires-Dist: click>=8.0.0; extra == 'dev'
Requires-Dist: fs; extra == 'dev'
Requires-Dist: moto[s3]>=5.0.0; extra == 'dev'
Requires-Dist: mypy>=0.990; extra == 'dev'
Requires-Dist: pandas; extra == 'dev'
Requires-Dist: pre-commit; extra == 'dev'
Requires-Dist: pylint>=2.14.0; extra == 'dev'
Requires-Dist: pytest-cov; extra == 'dev'
Requires-Dist: pytest-dependency; extra == 'dev'
Requires-Dist: pytest-mock; extra == 'dev'
Requires-Dist: pytest>=4.0.0; extra == 'dev'
Requires-Dist: ray[default]; extra == 'dev'
Requires-Dist: requests-mock; extra == 'dev'
Requires-Dist: twine; extra == 'dev'
Requires-Dist: types-python-dateutil; extra == 'dev'
Requires-Dist: types-requests; extra == 'dev'
Requires-Dist: types-urllib3; extra == 'dev'
Provides-Extra: docs
Requires-Dist: docutils; extra == 'docs'
Requires-Dist: ipython; extra == 'docs'
Requires-Dist: matplotlib; extra == 'docs'
Requires-Dist: nbsphinx; extra == 'docs'
Requires-Dist: sphinx-mdinclude==0.5.4; extra == 'docs'
Requires-Dist: sphinx-rtd-theme==1.3.0; extra == 'docs'
Requires-Dist: sphinx==7.1.2; extra == 'docs'
